{
	"name": "metalstructure_",
	"plugin-id": "Sprite",
	"sid": 679566039820401,
	"isGlobal": false,
	"instanceVariables": [],
	"behaviorTypes": [],
	"effectTypes": [],
	"animations": {
		"items": [
			{
				"frames": [
					{
						"width": 192,
						"height": 165,
						"originX": 0,
						"originY": 0,
						"originalSource": "",
						"exportFormat": "png",
						"exportQuality": 0.8,
						"imageSpriteId": 6564610,
						"collisionPoly": {
							"points": [
								1,
								0,
								1,
								1,
								0,
								1,
								0,
								0
							]
						},
						"useCollisionPoly": true,
						"duration": 1
					}
				],
				"sid": 457860296730278,
				"name": "Default",
				"isLooping": false,
				"isPingPong": false,
				"repeatCount": 1,
				"repeatTo": 0,
				"speed": 0
			}
		],
		"subfolders": []
	}
}